mindsponge/__init__.py
mindsponge/callback/__init__.py
mindsponge/callback/h5md.py
mindsponge/callback/information.py
mindsponge/cell/__init__.py
mindsponge/cell/amp.py
mindsponge/cell/basic.py
mindsponge/cell/equivariant.py
mindsponge/cell/initializer.py
mindsponge/cell/mask.py
mindsponge/cell/msa.py
mindsponge/cell/transition.py
mindsponge/cell/triangle.py
mindsponge/colvar/__init__.py
mindsponge/colvar/atoms.py
mindsponge/colvar/base.py
mindsponge/colvar/bonded.py
mindsponge/colvar/colvar.py
mindsponge/colvar/index.py
mindsponge/colvar/position.py
mindsponge/common/__init__.py
mindsponge/common/config_load.py
mindsponge/common/geometry.py
mindsponge/common/protein.py
mindsponge/common/residue_constants.py
mindsponge/common/stereo_chemical_props.txt
mindsponge/common/utils.py
mindsponge/control/__init__.py
mindsponge/control/controller.py
mindsponge/control/barostat/__init__.py
mindsponge/control/barostat/barostat.py
mindsponge/control/barostat/berendsen.py
mindsponge/control/constraint/__init__.py
mindsponge/control/constraint/constraint.py
mindsponge/control/constraint/lincs.py
mindsponge/control/integrator/__init__.py
mindsponge/control/integrator/brownian.py
mindsponge/control/integrator/integrator.py
mindsponge/control/integrator/leapfrog.py
mindsponge/control/integrator/velocityverlet.py
mindsponge/control/thermostat/__init__.py
mindsponge/control/thermostat/berendsen.py
mindsponge/control/thermostat/langevin.py
mindsponge/control/thermostat/thermostat.py
mindsponge/core/__init__.py
mindsponge/core/sponge.py
mindsponge/core/analysis/__init__.py
mindsponge/core/analysis/analyse.py
mindsponge/core/simulation/__init__.py
mindsponge/core/simulation/run.py
mindsponge/core/simulation/simulation.py
mindsponge/core/wrapper/__init__.py
mindsponge/core/wrapper/its.py
mindsponge/core/wrapper/remd.py
mindsponge/core/wrapper/summation.py
mindsponge/core/wrapper/wrapper.py
mindsponge/data/__init__.py
mindsponge/data/data.py
mindsponge/data/data_transform.py
mindsponge_ascend-1.0.0rc1.dist-info/METADATA
mindsponge_ascend-1.0.0rc1.dist-info/WHEEL
mindsponge_ascend-1.0.0rc1.dist-info/top_level.txt
mindsponge_ascend-1.0.0rc1.dist-info/RECORD
