Metadata-Version: 2.1
Name: mindsponge-ascend
Version: 1.0.0rc1
Summary: simulation package of next generation molecular modeling in mindspore
Home-page: https://www.mindspore.cn/
Author: The MindSpore Authors
Author-email: contact@mindspore.cn
License: Apache 2.0
Download-URL: https://gitee.com/mindspore/mindscience/tags
Project-URL: Sources, https://gitee.com/mindspore/mindscience
Project-URL: Issue Tracker, https://gitee.com/mindspore/mindscience/issues
Platform: UNKNOWN
Classifier: License :: OSI Approved :: Apache Software License
Requires-Dist: numpy (>=1.17.0)
Requires-Dist: biopython (>=1.79)
Requires-Dist: pyyaml (>=5.4.1)
Requires-Dist: dataclasses (>=0.6)
Requires-Dist: glob2 (>=0.6)
Requires-Dist: h5py (>=3.6.0)
Requires-Dist: absl-py (>=1.1.0)
